ucodeio_hellolib/__init__.py
ucodeio_hellolib/hello.py
ucodeio_hellolib-0.3.dist-info/LICENSE
ucodeio_hellolib-0.3.dist-info/METADATA
ucodeio_hellolib-0.3.dist-info/WHEEL
ucodeio_hellolib-0.3.dist-info/top_level.txt
ucodeio_hellolib-0.3.dist-info/RECORD
