Metadata-Version: 2.1
Name: ucodeio_hellolib
Version: 0.3
Summary: A simple hello library and function that returns hello <name>
Home-page: http://github.com/sstacha/ucodeio_hellolib
Author: Steve Stacha
Author-email: sstacha@gmail.com
License: MIT
Classifier: Programming Language :: Python :: 3
Classifier: License :: OSI Approved :: MIT License
Classifier: Operating System :: OS Independent
Requires-Python: >=3.9
License-File: LICENSE
